{
  "project_info": {
    "project_number": "855364517437",
    "project_id": "winter-2024-31dd0",
    "storage_bucket": "winter-2024-31dd0.firebasestorage.app"
  },
  "client": [
    {
      "client_info": {
        "mobilesdk_app_id": "1:855364517437:android:79d0c039a70a9fdf033454",
        "android_client_info": {
          "package_name": "com.example.firebase_1"
        }
      },
      "oauth_client": [],
      "api_key": [
        {
          "current_key": "AIzaSyAMdmD5WWNfGGfVtNTUTs35-cF0-VlDOG4"
        }
      ],
      "services": {
        "appinvite_service": {
          "other_platform_oauth_client": []
        }
      }
    }
  ],
  "configuration_version": "1"
}